README.md
setup.py
ggoogle.egg-info/PKG-INFO
ggoogle.egg-info/SOURCES.txt
ggoogle.egg-info/dependency_links.txt
ggoogle.egg-info/entry_points.txt
ggoogle.egg-info/requires.txt
ggoogle.egg-info/top_level.txt
utils/__init__.py
utils/__main__.py