Metadata-Version: 2.1
Name: ggoogle
Version: 1.3
Summary: UNKNOWN
Home-page: UNKNOWN
License: UNKNOWN
Platform: UNKNOWN
